source_to_text_converter/__init__.py
source_to_text_converter/source_to_text_converter.py
tests/__init__.py
tests/base_test.py
tests/test_codebase_to_text.py
tests/test_codebase_to_text_expanded.py
tests/test_integration_performance.py
source_to_text_converter-0.1.2.dist-info/METADATA
source_to_text_converter-0.1.2.dist-info/WHEEL
source_to_text_converter-0.1.2.dist-info/entry_points.txt
source_to_text_converter-0.1.2.dist-info/top_level.txt
source_to_text_converter-0.1.2.dist-info/RECORD
