Metadata-Version: 2.4
Name: source-to-text-converter
Version: 0.1.2
Summary: A tool to convert source code to text or docx
Home-page: https://github.com/fisamy/source-to-text-converter
Author: fisamy
Author-email: fisamy@example.com
Classifier: Programming Language :: Python :: 3
Classifier: License :: OSI Approved :: Apache Software License
Classifier: Operating System :: OS Independent
Requires-Python: >=3.6
Requires-Dist: gitpython
Requires-Dist: python-docx
Dynamic: author
Dynamic: author-email
Dynamic: classifier
Dynamic: description
Dynamic: description-content-type
Dynamic: home-page
Dynamic: requires-dist
Dynamic: requires-python
Dynamic: summary
